{
  "active_plan": "C:\\Users\\Raum\\Documents\\InfoBrain\\program-poj\\linkfs\\vhdx-rs\\.sisyphus\\plans\\fix-plan-impl-gaps.md",
  "started_at": "2026-04-19T14:16:28.952Z",
  "session_ids": [
    "ses_25a441342ffeV8SeDWB6hA5sAn",
    "ses_259e5d1e8ffeT0iNaj5dyyC3N9",
    "ses_259e5d171ffee0uE5tSTodaBbb",
    "ses_259e5d16cffebewBlTDVQ2Ouz2"
  ],
  "session_origins": {
    "ses_25a441342ffeV8SeDWB6hA5sAn": "direct",
    "ses_259e5d1e8ffeT0iNaj5dyyC3N9": "appended",
    "ses_259e5d171ffee0uE5tSTodaBbb": "appended",
    "ses_259e5d16cffebewBlTDVQ2Ouz2": "appended"
  },
  "plan_name": "fix-plan-impl-gaps",
  "agent": "atlas",
  "task_sessions": {
    "todo:1": {
      "task_key": "todo:1",
      "task_label": "1",
      "task_title": "修复 Dynamic 读路径按 BAT 读取已分配块",
      "session_id": "ses_259e0d615ffetY49BmWEZPeQaY",
      "agent": "Sisyphus-Junior",
      "category": "deep",
      "updated_at": "2026-04-19T14:27:39.425Z"
    },
    "todo:2": {
      "task_key": "todo:2",
      "task_label": "2",
      "task_title": "让 ReplayOverlay 在 Dynamic 读路径生效",
      "session_id": "ses_259da01beffexMZQseuZZiH3u2",
      "agent": "Sisyphus-Junior",
      "category": "unspecified-high",
      "updated_at": "2026-04-19T14:47:30.984Z"
    },
    "todo:3": {
      "task_key": "todo:3",
      "task_label": "3",
      "task_title": "修正 Dynamic 写路径对 BAT payload entry 的索引与状态处理",
      "session_id": "ses_259c791edffeyI46jHeZDzQF7Y",
      "agent": "Sisyphus-Junior",
      "category": "deep",
      "updated_at": "2026-04-19T14:55:38.601Z"
    },
    "todo:4": {
      "task_key": "todo:4",
      "task_label": "4",
      "task_title": "实现 `check` 命令真实校验流程（接入 SpecValidator）",
      "session_id": "ses_259bc8e73ffelceQaZ3UzX6wK5",
      "agent": "Sisyphus-Junior",
      "category": "unspecified-high",
      "updated_at": "2026-04-19T15:07:39.470Z"
    },
    "todo:5": {
      "task_key": "todo:5",
      "task_label": "5",
      "task_title": "落地 `check --log-replay` 与 `check --repair` 语义（去除 not implemented）",
      "session_id": "ses_259b29801ffeNyt8e33nJ9N0tr",
      "agent": "Sisyphus-Junior",
      "category": "quick",
      "updated_at": "2026-04-19T15:19:13.101Z"
    },
    "todo:6": {
      "task_key": "todo:6",
      "task_label": "6",
      "task_title": "实现 `sections log` 真实输出",
      "session_id": "ses_259aa5cd1ffePXQEj74PeRrnrK",
      "agent": "Sisyphus-Junior",
      "category": "quick",
      "updated_at": "2026-04-19T15:26:33.062Z"
    },
    "todo:7": {
      "task_key": "todo:7",
      "task_label": "7",
      "task_title": "实现 `diff chain` 真实链路遍历",
      "session_id": "ses_259a493d2ffeTH0SLCQptIqrei",
      "agent": "Sisyphus-Junior",
      "category": "unspecified-high",
      "updated_at": "2026-04-19T15:37:15.608Z"
    },
    "todo:8": {
      "task_key": "todo:8",
      "task_label": "8",
      "task_title": "对齐 README 与 CLI 契约文档（包名/参数/值）",
      "session_id": "ses_2599ac01effe25c12azzZEFYqn",
      "agent": "Sisyphus-Junior",
      "category": "writing",
      "updated_at": "2026-04-19T15:42:10.030Z"
    },
    "todo:9": {
      "task_key": "todo:9",
      "task_label": "9",
      "task_title": "补齐/更新回归测试（库 + CLI）",
      "session_id": "ses_25994701bffe3DjO288jsf1pDB",
      "agent": "Sisyphus-Junior",
      "category": "unspecified-high",
      "updated_at": "2026-04-19T16:03:57.194Z"
    },
    "todo:10": {
      "task_key": "todo:10",
      "task_label": "10",
      "task_title": "全量回归、构建与证据归档",
      "session_id": "ses_2597f0043ffe4hPeMvVtPPVGcv",
      "agent": "Sisyphus-Junior",
      "category": "unspecified-high",
      "updated_at": "2026-04-19T16:12:23.786Z"
    },
    "final-wave:f1": {
      "task_key": "final-wave:f1",
      "task_label": "F1",
      "task_title": "Plan Compliance Audit — oracle",
      "session_id": "ses_25979ddcfffejZXp174gRYzpKJ",
      "agent": "oracle",
      "category": "",
      "updated_at": "2026-04-19T16:19:56.796Z"
    }
  }
}